xerotrust/__init__.py
xerotrust/authentication.py
xerotrust/check.py
xerotrust/exceptions.py
xerotrust/export.py
xerotrust/jsonl.py
xerotrust/main.py
xerotrust/py.typed
xerotrust/reconcile.py
xerotrust/transform.py
xerotrust/templates/error.html
xerotrust/templates/styles.html
xerotrust/templates/success.html
xerotrust-1.1.0.dist-info/METADATA
xerotrust-1.1.0.dist-info/WHEEL
xerotrust-1.1.0.dist-info/entry_points.txt
xerotrust-1.1.0.dist-info/licenses/LICENSE.txt
xerotrust-1.1.0.dist-info/RECORD
