Metadata-Version: 2.4
Name: xerotrust
Version: 1.1.0
Summary: Export and explore data from Xero accounts.
Project-URL: Homepage, https://xerotrust.readthedocs.io/
Project-URL: Documentation, https://xerotrust.readthedocs.io/
Project-URL: Repository, https://github.com/cjw296/xerotrust
Author-email: Chris Withers <chris@withers.org>
License-File: LICENSE.txt
Requires-Python: >=3.13
Requires-Dist: click>=8.2
Requires-Dist: enlighten>=1.14.1
Requires-Dist: fastapi>=0.115.12
Requires-Dist: hypercorn>=0.17.3
Requires-Dist: jinja2>=3.1.6
Requires-Dist: pook>=2.1.3
Requires-Dist: python-dateutil>=2.9.0.post0
Requires-Dist: pyxero>=0.9.5
Requires-Dist: rich>=13.7
